<?xml version="1.0" encoding="ISO-8859-1"?>
<actions>
    <action>
        <actionName>run</actionName>
        <goals>
            <goal>package</goal>
        </goals>
        <properties>
            <netbeans.deploy>true</netbeans.deploy>
            <skipTests>true</skipTests>
        </properties>
    </action>
    <action>
        <actionName>debug</actionName>
        <goals>
            <goal>package</goal>
        </goals>
        <properties>
            <netbeans.deploy.debugmode>true</netbeans.deploy.debugmode>
            <netbeans.deploy>true</netbeans.deploy>
            <skipTests>true</skipTests>
        </properties>
    </action>
    <action>
        <actionName>CUSTOM-Build -skip-test</actionName>
        <displayName>Build -skip-test</displayName>
        <goals>
            <goal>install</goal>
        </goals>
        <properties>
            <skipTests>true</skipTests>
        </properties>
    </action>
    <action>
        <actionName>CUSTOM-Run -skip-test</actionName>
        <displayName>Run -skip-test</displayName>
        <goals>
            <goal>package</goal>
        </goals>
        <properties>
            <skipTests>true</skipTests>
            <netbeans.deploy>true</netbeans.deploy>
        </properties>
    </action>
    <action>
        <actionName>CUSTOM-Debug -skip-test</actionName>
        <displayName>Debug -skip-test</displayName>
        <goals>
            <goal>package</goal>
        </goals>
        <properties>
            <netbeans.deploy.debugmode>true</netbeans.deploy.debugmode>
            <netbeans.deploy>true</netbeans.deploy>
            <skipTests>true</skipTests>
        </properties>
    </action>
    <action>
        <actionName>CUSTOM-Build site</actionName>
        <displayName>Build site</displayName>
        <goals>
            <goal>site</goal>
        </goals>
    </action>
    <action>
        <actionName>CUSTOM-Run Cobertura</actionName>
        <displayName>Run Cobertura</displayName>
        <goals>
            <goal>cobertura:cobertura</goal>
        </goals>
    </action>

</actions>
